<?xml version="1.0" encoding="utf-8"?>
<translations>
   <translation id="cpcipnd_create_title" qtlid="331202">Add Private Network</translation>
   <translation id="cpcipnd_default_name_template" qtlid="331215">VLAN{{id}}</translation>
   <translation id="cpcipnd_name_label" qtlid="3818">Name</translation>
   <translation id="cpcipnd_name_required_error" qtlid="331228">The name is mandatory.</translation>
   <translation id="cpcipnd_name_maxlength_error" qtlid="331241">The name of your private network cannot have more than 256 characters.</translation>
   <translation id="cpcipnd_vlan_create" qtlid="348347">Defining a VLAN</translation>
   <translation id="cpcipnd_vlan_description" qtlid="348360">You can define a VLAN between {{ min }} and {{ max }}. This is useful for dividing your vRack between many virtual networks. </translation>
   <translation id="cpcipnd_vlanId_label" qtlid="348373">VLAN ID:</translation>
   <translation id="cpcipnd_vlanId_number_helper" qtlid="348386">(between {{ min }} and {{ max }})</translation>
   <translation id="cpcipnd_vlanId_required_error" qtlid="331267">The ID is mandatory.</translation>
   <translation id="cpcipnd_vlanId_number_error" qtlid="331280">The ID of the private network must be between 1 and 4000.</translation>
   <translation id="cpcipnd_vlanId_unique_error" qtlid="331293">ID is already in use.</translation>
   <translation id="cpcipnd_region_label" qtlid="331306">Associate to region</translation>
   <translation id="cpcipnd_region_default_option" qtlid="331319">All regions</translation>
   <translation id="cpcipnd_regions_query_error" qtlid="331332">Oh snap, regions could not be retrieved. {{ message }}</translation>
   <translation id="cpcipnd_region_hint" qtlid="331345">More information on <a href="{{ url }}" target="_blank">multi-region</a> private networks.</translation>
   <translation id="cpcipnd_subnet_label" qtlid="331358">Private Network Address (CIDR) :</translation>
   <translation id="cpcipnd_subnet_address_required_error" qtlid="331371">The address is mandatory.</translation>
   <translation id="cpcipnd_subnet_address_valid_ip_address_error" qtlid="331384">The address format is invalid.</translation>
   <translation id="cpcipnd_subnet_address_hint" qtlid="30430">Address</translation>
   <translation id="cpcipnd_subnet_address_title" qtlid="331397">Subnet address</translation>
   <translation id="cpcipnd_subnet_range_label" qtlid="331410">Range :</translation>
   <translation id="cpcipnd_subnet_mask_hint" qtlid="331423">24</translation>
   <translation id="cpcipnd_subnet_mask_required_error" qtlid="331436">The mask is mandatory.</translation>
   <translation id="cpcipnd_subnet_mask_number_error" qtlid="331449">The mask is invalid.</translation>
   <translation id="cpcipnd_subnet_mask_title" qtlid="311024">Subnet Mask</translation>
   <translation id="cpcipnd_subnet_dhcp_label" qtlid="331462">Address distribution:</translation>
   <translation id="cpcipnd_subnet_dhcp_on_label" qtlid="331475">Dynamic (DHCP)</translation>
   <translation id="cpcipnd_subnet_dhcp_off_label" qtlid="331488">Static (Manual)</translation>
   <translation id="cpcipnd_subnet_start_label" qtlid="331501">Range Start (DHCP)</translation>
   <translation id="cpcipnd_subnet_start_required_error" qtlid="331514">This configuration is mandatory.</translation>
   <translation id="cpcipnd_subnet_start_valid_ip_address_error" qtlid="331384">The address format is invalid.</translation>
   <translation id="cpcipnd_subnet_end_label" qtlid="331527">End of range (DHCP)</translation>
   <translation id="cpcipnd_subnet_end_required_error" qtlid="331514">This configuration is mandatory.</translation>
   <translation id="cpcipnd_subnet_end_valid_ip_address_error" qtlid="331384">The address format is invalid.</translation>
   <translation id="cpcipnd_save_button" qtlid="331540">Create Private Network</translation>
   <translation id="cpcipnd_cancel_button" qtlid="37863">Cancel</translation>
   <translation id="cpcipnd_fetch_regions_error" qtlid="331553">Oh snap, regions could not be retrieved.</translation>
   <translation id="cpcipnd_fetch_private_networks_error" qtlid="303978">Oh snap, the list of private networks could not be retrieved. </translation>
   <translation id="cpcipnd_fetch_private_network_error" qtlid="331566">Oh snap, the private network could not be retrieved.</translation>
   <translation id="cpcipnd_save_error" qtlid="331579">Oh snap, the private could not be saved. {{ message }}</translation>
   <translation id="cpcipnd_subnet_save_error" qtlid="331592">Oh snap, the subnet could not be saved. {{ message }}</translation>
   <translation id="cpcipnd_request_error" qtlid="331605">Oh snap, an error occurred while loading the form. {{ message }}</translation>
   <translation id="cpcipnd_common_menu_item_description" qtlid="331618">Private Network Configuration</translation>
   <translation id="cpcipnd_subnets_menu_item_description" qtlid="331631">Subnet Configuration</translation>
   <translation id="cpcipnd_subnet_api_notice" qtlid="331644">You can customize your ranges <a href="{{url}}" target="_blank">using our API.</a></translation>
   <translation id="cpcipnd_subnet_gateway_label" qtlid="405525">Activate the default gateway </translation>
</translations>
