<?xml version="1.0" encoding="utf-8"?>
<translations>
   <translation id="iplb_ssl_certificate_title" qtlid="371307">Certificati SSL</translation>
   <translation id="iplb_ssl_certificate_intro_text" qtlid="438987">I certificati configurati sono automaticamente disponibili per tutti i frontend su cui è attiva l'opzione SSL.</translation>

   <translation id="iplb_ssl_certificate_add" qtlid="420723">Aggiungi un certificato SSL</translation>

   <translation id="iplb_ssl_certificate" qtlid="19771">Certificato</translation>
   <translation id="iplb_ssl_subject" qtlid="22639">Oggetto</translation>
   <translation id="iplb_ssl_type" qtlid="2642">Tipo</translation>
   <translation id="iplb_ssl_action" qtlid="56105">Azione</translation>
   <translation id="iplb_ssl_no_certificate" qtlid="439000">Nessun certificato</translation>

   <translation id="iplb_ssl_see" qtlid="433371">Visualizza l'anteprima</translation>
   <translation id="iplb_ssl_update" qtlid="37875">Modifica</translation>
   <translation id="iplb_ssl_delete" qtlid="2414">Elimina</translation>

   <translation id="iplb_ssl_list_error" qtlid="439013">Errore surante il caricamento della lista dei certificati.</translation>

   <translation id="iplb_ssl_add_title" qtlid="420723">Aggiungi un certificato SSL</translation>
   <translation id="iplb_ssl_order_title" qtlid="196803">Ordina un certificato SSL</translation>
   <translation id="iplb_ssl_add_confirm" qtlid="37923">Aggiungi</translation>
   <translation id="iplb_ssl_add_cancel" qtlid="37863">Annulla</translation>
   <translation id="iplb_ssl_add_success" qtlid="439026">Il certificato SSL è stato creato correttamente.</translation>
   <translation id="iplb_ssl_add_error" qtlid="439039">Si è verificato un errore durante la creazione del certificato SSL: {{message}}</translation>

   <translation id="iplb_ssl_edit_name" qtlid="415818">Nome (facoltativo)</translation>
   <translation id="iplb_ssl_edit_private_key" qtlid="19795">Chiave privata</translation>
   <translation id="iplb_ssl_edit_certificate" qtlid="19771">Certificato</translation>
   <translation id="iplb_ssl_edit_chain" qtlid="439052">Chain (opzionale)</translation>

   <translation id="iplb_ssl_update_title" qtlid="439065">Modifica un certificato SSL</translation>
   <translation id="iplb_ssl_update_confirm" qtlid="37875">Modifica</translation>
   <translation id="iplb_ssl_update_cancel" qtlid="37863">Annulla</translation>
   <translation id="iplb_ssl_update_nom" qtlid="3818">Nome</translation>
   <translation id="iplb_ssl_update_success" qtlid="439078">Il certificato SSL è stato modificato correttamente.</translation>
   <translation id="iplb_ssl_update_error" qtlid="439091">Si è verificato un errore durante la modifica del certificato SSL: {{message}}</translation>

   <translation id="iplb_ssl_preview_title" qtlid="439104">Anteprima certificato SSL</translation>
   <translation id="iplb_ssl_preview_name" qtlid="3818">Nome</translation>
   <translation id="iplb_ssl_preview_serial" qtlid="429758">Numero di sequenza</translation>
   <translation id="iplb_ssl_preview_subject" qtlid="22639">Oggetto</translation>
   <translation id="iplb_ssl_preview_fingerprint" qtlid="192344">Traccia</translation>
   <translation id="iplb_ssl_preview_type" qtlid="2642">Tipo</translation>
   <translation id="iplb_ssl_preview_id" qtlid="46792">Identificativo</translation>

   <translation id="iplb_ssl_delete_title" qtlid="439117">Elimina un certificato</translation>
   <translation id="iplb_ssl_delete_question" qtlid="439130">Vuoi davvero eliminare il certificato {{name}}?</translation>
   <translation id="iplb_ssl_delete_button" qtlid="2414">Elimina</translation>
   <translation id="iplb_ssl_delete_success" qtlid="439143">Il certificato SSL è stato eliminato correttamente.</translation>
   <translation id="iplb_ssl_delete_error" qtlid="439156">Si è verificato un errore durante l'eliminazione del certificato SSL: {{message}}</translation>

   <translation id="iplb_ssl_order_name" qtlid="415818">Nome (facoltativo)</translation>
   <translation id="iplb_ssl_order_type" qtlid="439169">Tipo di certificato</translation>
   <translation id="iplb_ssl_order_type_free" qtlid="130495">Gratuito</translation>
   <translation id="iplb_ssl_order_type_dv" qtlid="439182">Comodo DV</translation>
   <translation id="iplb_ssl_order_type_ev" qtlid="439195">Comodo EV</translation>
   <translation id="iplb_ssl_order_type_free" qtlid="130495">Gratuito</translation>
   <translation id="iplb_ssl_order_fqdn" qtlid="439208">Fully Qualified Domain Name (FQDN)</translation>
   <translation id="iplb_ssl_order_fqdn_tip" qtlid="439221">example.com, www.example.com</translation>
   <translation id="iplb_ssl_order_contact" qtlid="31066">Contatto</translation>
   <translation id="iplb_ssl_order_email" qtlid="439234">Indirizzo di posta elettronica</translation>
   <translation id="iplb_ssl_order_business_category" qtlid="431851">Categoria dell'Organizzazione</translation>
   <translation id="iplb_ssl_order_country" qtlid="25171">Paese</translation>
   <translation id="iplb_ssl_order_state_or_province" qtlid="439247">Stato o Provincia</translation>
   <translation id="iplb_ssl_order_incorporation_date" qtlid="431799">Data di incorporazione</translation>
   <translation id="iplb_ssl_order_organisation_name" qtlid="191109">Nome azienda</translation>
   <translation id="iplb_ssl_order_unit_name" qtlid="439260">Nome dell'unità organizzativa</translation>
   <translation id="iplb_ssl_order_address" qtlid="30430">Indirizzo</translation>
   <translation id="iplb_ssl_order_postal_code" qtlid="30346">Codice postale</translation>
   <translation id="iplb_ssl_order_city" qtlid="33310">Città</translation>
   <translation id="iplb_ssl_order_joi" qtlid="439273">Giurisdizione dell'incorporazione</translation>

   <translation id="iplb_ssl_order_ok" qtlid="43558">Ordina</translation>
   <translation id="iplb_ssl_order_cancel" qtlid="37863">Annulla</translation>
</translations>
