<?xml version="1.0" encoding="utf-8"?>
<translations>
   <translation id="cpd_project_redirect" qtlid="245857">Redirecting...</translation>

   <translation id="cpd_project_suspended" qtlid="263858">Your cloud project is suspended. For more information, please contact <a href="#/support">support</a>.</translation>

   <translation id="cpd_project_creating_help" qtlid="245896">You will be automatically redirected once your project has been created.</translation>
   <translation id="cpd_project_creating_havetopay" qtlid="272014">Veuillez finaliser le paiement de votre bon de commande initial.</translation>
   <translation id="cpd_project_creating_cancel" qtlid="281990">Cancel project creation</translation>
   <translation id="cpd_project_creating_bc_havetopay" qtlid="272027">Please finalize the payment for your <a href="{{url}}" target="_blank"> original purchase order</a>.</translation>
   <translation id="cpd_project_creating_bc_support" qtlid="286812">If this page does not disappear several minutes after payment, please contact <a href="#/support">our support team</a>.</translation>

   <translation id="cpd_project_deleting" qtlid="245909">Deleting project...</translation>
   <translation id="cpd_project_deleting_help" qtlid="245922">You will be automatically redirected once your project has been deleted.</translation>

   <translation id="cpd_project_created" qtlid="245935">Your project is ready!</translation>

   <translation id="cpd_project_cancel_success" qtlid="282003">Project creation has been cancelled.</translation>
   <translation id="cpd_project_cancel_error_expired_status" qtlid="282016">Your project has expired.</translation>
   <translation id="cpd_project_cancel_error_ok_status" qtlid="282029">Your project has already been created.</translation>
   <translation id="cpd_project_cancel_error" qtlid="282042">An error occurred during cancellation.</translation>
</translations>
